dbf_read_iffy.py
setup.py
dbf_read_iffy.egg-info/PKG-INFO
dbf_read_iffy.egg-info/SOURCES.txt
dbf_read_iffy.egg-info/dependency_links.txt
dbf_read_iffy.egg-info/requires.txt
dbf_read_iffy.egg-info/top_level.txt