Metadata-Version: 1.1
Name: dbf-read-iffy
Version: 1.0.2
Summary: Read from dbf's if codepage is unsupported by modules dbf and codecs (895 cz Kamenicky, ..).
Home-page: https://github.com/zvolsky/dbf_read_iffy
Author: Mirek Zvolsky
Author-email: zvolsky@seznam.cz
License: UNKNOWN
Download-URL: https://github.com/zvolsky/dbf_read_iffy/tarball/1.0
Keywords: dbf,dbase,foxpro,vfp,encoding,895,Kamenicky,620,Mazovia
Platform: UNKNOWN
Classifier: Development Status :: 4 - Beta
Classifier: Intended Audience :: Developers
Classifier: Intended Audience :: Information Technology
Classifier: License :: OSI Approved :: MIT License
Classifier: Operating System :: OS Independent
Classifier: Topic :: Database
Classifier: Topic :: Database :: Database Engines/Servers
Classifier: Topic :: Software Development
Classifier: Programming Language :: Python
Classifier: Programming Language :: Python :: 2
Classifier: Programming Language :: Python :: 3
